omnicon_ddsdocgen/ComparisonModule.py
omnicon_ddsdocgen/DocCompareLogic.py
omnicon_ddsdocgen/DocGenInterface.py
omnicon_ddsdocgen/DocGenLogic.py
omnicon_ddsdocgen/DocumentHandler.py
omnicon_ddsdocgen/DocxGen.py
omnicon_ddsdocgen/ErrorListHandler.py
omnicon_ddsdocgen/GeneralFunctions.py
omnicon_ddsdocgen/HtmlGen.py
omnicon_ddsdocgen/Logger.py
omnicon_ddsdocgen/OmniconEngineHandler.py
omnicon_ddsdocgen/Omnicon_DDSDocGen.py
omnicon_ddsdocgen/PdfGen.py
omnicon_ddsdocgen/SharedEnums.py
omnicon_ddsdocgen/SingleChapterGenerator.py
omnicon_ddsdocgen/Template.docx
omnicon_ddsdocgen/Template.html
omnicon_ddsdocgen/Utils.py
omnicon_ddsdocgen/__init__.py
omnicon_ddsdocgen/comp.py
omnicon_ddsdocgen-3.2.2.dist-info/licenses/LICENSE
omnicon_ddsdocgen-3.2.2.dist-info/METADATA
omnicon_ddsdocgen-3.2.2.dist-info/WHEEL
omnicon_ddsdocgen-3.2.2.dist-info/top_level.txt
omnicon_ddsdocgen-3.2.2.dist-info/RECORD
