Metadata-Version: 2.4
Name: omnicon_ddsdocgen
Version: 3.2.2
Summary: DDS Document Generator
Home-page: https://www.OmniconSystems.com
Author-email: Omnicon Distributed Systems LTD <info@OmniconSystems.com>
Classifier: License :: Other/Proprietary License
Classifier: Programming Language :: Python :: 3
Classifier: Operating System :: Microsoft :: Windows
Classifier: Operating System :: POSIX :: Linux
Classifier: Topic :: Communications
Classifier: Topic :: Documentation
Requires-Python: <4.0
License-File: LICENSE
Requires-Dist: build==0.9.0
Requires-Dist: colorama==0.4.6
Requires-Dist: docx2pdf==0.1.8
Requires-Dist: importlib-metadata==5.0.0
Requires-Dist: importlib-resources==5.10.0
Requires-Dist: lxml==5.3.0
Requires-Dist: Omnicon-GenericDDSEngine-Py==4.6.3.post1
Requires-Dist: pep517==0.13.0
Requires-Dist: pyparsing==3.0.9
Requires-Dist: python-docx==0.8.11
Requires-Dist: tomli==2.0.1
Requires-Dist: tqdm==4.64.1
Requires-Dist: typing_extensions==4.12.2
Requires-Dist: zipp==3.19.1
Requires-Dist: beautifulsoup4==4.12.3
Requires-Dist: cssutils==2.7.1
Requires-Dist: pywin32==306; platform_system == "Windows"
Dynamic: license-file
